dngsmgmt/__init__.py
dngsmgmt/admin.py
dngsmgmt/api.py
dngsmgmt/forms.py
dngsmgmt/models.py
dngsmgmt/permissions.py
dngsmgmt/serializers.py
dngsmgmt/urls.py
dngsmgmt/views.py
dngsmgmt/tests/__init__.py
dngsmgmt/tests/create_data.py
dngsmgmt/tests/create_data_condition.py
dngsmgmt/tests/create_data_experiment.py
dngsmgmt/tests/create_data_project.py
dngsmgmt/tests/create_data_sample.py
dngsmgmt/tests/create_data_users.py
dngsmgmt/tests/settings.py
dngsmgmt/tests/test_models.py
dngsmgmt/tests/test_response.py
dngsmgmt/tests/test_response_condition.py
dngsmgmt/tests/test_response_experiment.py
dngsmgmt/tests/test_response_project.py
dngsmgmt/tests/test_response_sample.py
dngsmgmt/tests/urls.py
dngsmgmt-0.0.1a3.dist-info/LICENSE
dngsmgmt-0.0.1a3.dist-info/METADATA
dngsmgmt-0.0.1a3.dist-info/WHEEL
dngsmgmt-0.0.1a3.dist-info/top_level.txt
dngsmgmt-0.0.1a3.dist-info/RECORD
