Metadata-Version: 2.1
Name: dngsmgmt
Version: 0.0.1a3
Summary: UNKNOWN
Home-page: https://gitlab.com/r78v10a07/dngsmgmt
Maintainer: Vera Alvarez, Roberto
Maintainer-email: veraalva@ncbi.nlm.nih.gov
License: Public Domain
Platform: UNKNOWN
Classifier: Development Status :: 3 - Alpha
Classifier: Environment :: Web Environment
Classifier: Framework :: Django :: 2.1
Classifier: Intended Audience :: Science/Research
Classifier: License :: Public Domain
Classifier: Natural Language :: English
Classifier: Operating System :: Unix
Classifier: Programming Language :: Python :: 3 :: Only
Classifier: Topic :: Scientific/Engineering :: Bio-Informatics
Requires-Dist: uWSGI
Requires-Dist: Django
Requires-Dist: django-appconf
Requires-Dist: django-compressor
Requires-Dist: django-filter
Requires-Dist: django-extensions
Requires-Dist: djangorestframework
Requires-Dist: settings-overrider
